setup.py
cloudyvents/__init__.py
cloudyvents/cyvents.py
cloudyvents.egg-info/PKG-INFO
cloudyvents.egg-info/SOURCES.txt
cloudyvents.egg-info/dependency_links.txt
cloudyvents.egg-info/requires.txt
cloudyvents.egg-info/top_level.txt
cloudyvents/tests/__init__.py
cloudyvents/tests/test_cyvents.py