Metadata-Version: 1.0
Name: cloudyvents
Version: 0.1
Summary: An event management library for the EPU services.
Home-page: http://www.nimbusproject.org/
Author: Nimbus Team
Author-email: nimbus@mcs.anl.gov
License: Apache2
Platform: UNKNOWN
